{"template":"/Users/tainguyen/neo-one/packages/neo-one-website/src/pages/reference","sharedHashesByProp":{},"data":{"title":"JSONRPCRequest","slug":"/reference/@neo-one/client/jsonrpcrequest","content":{"type":"referenceItem","value":{"name":"JSONRPCRequest","type":"Interface","slug":"/reference/@neo-one/client/jsonrpcrequest","definition":[{"value":"export"},{"value":"interface"},{"slug":"/reference/@neo-one/client/jsonrpcrequest","value":"JSONRPCRequest"},{"value":""},{"value":"{"},{"value":""},{"value":"\n"},{"value":""},{"value":"readonly"},{"value":"method"},{"value":":"},{"value":""},{"value":"string"},{"value":";"},{"value":""},{"value":"\n"},{"value":""},{"value":"readonly"},{"value":"params?"},{"value":":"},{"value":""},{"value":"any"},{"value":";"},{"value":""},{"value":"\n"},{"value":""},{"value":"readonly"},{"value":"watchTimeoutMS?"},{"value":":"},{"value":""},{"value":"number"},{"value":";"},{"value":""},{"value":"\n"},{"value":"}"},{"value":""}],"description":[{"value":"jsonrpc"},{"value":"request"},{"value":"object"},{"value":"."},{"value":""}],"interfaceData":{"properties":[{"name":"method","type":[{"value":"string"}],"description":[{"value":"Method"},{"value":"to"},{"value":"be"},{"value":"invoked"},{"value":"."},{"value":""}]},{"name":"params","type":[{"value":"any"}],"description":[{"value":"Invocation"},{"value":"params"},{"value":"."},{"value":""}]},{"name":"watchTimeoutMS","type":[{"value":"number"}],"description":[{"value":"How"},{"value":"long"},{"value":"to"},{"value":"leave"},{"value":"the"},{"value":"request"},{"value":"open"},{"value":""},{"value":"("},{"value":"i"},{"value":"."},{"value":"e"},{"value":"."},{"value":""},{"value":"long-polling"},{"value":")"},{"value":""},{"value":"to"},{"value":"wait"},{"value":"for"},{"value":"a"},{"value":"result"},{"value":"for"},{"value":"given"},{"value":"method"},{"value":"and"},{"value":"params"},{"value":"."},{"value":""}]}],"methods":[]}}},"current":"/reference/@neo-one/client","sidebar":[{"title":"Packages","subsections":[{"slug":"/reference/@neo-one/client","title":"@neo-one/client"},{"slug":"/reference/@neo-one/smart-contract","title":"@neo-one/smart-contract"}]}]},"path":"reference/@neo-one/client/jsonrpcrequest"}
