{"template":"/Users/tainguyen/neo-one/packages/neo-one-website/src/pages/reference","sharedHashesByProp":{},"data":{"title":"Hash160ABI","slug":"/reference/@neo-one/client/hash160abi","content":{"type":"referenceItem","value":{"name":"Hash160ABI","type":"Type Alias","slug":"/reference/@neo-one/client/hash160abi","definition":[{"value":"export"},{"value":"type"},{"slug":"/reference/@neo-one/client/hash160abi","value":"Hash160ABI"},{"value":"="},{"slug":"/reference/@neo-one/client/hash160abiparameter","value":"Hash160ABIParameter"},{"value":"|"},{"slug":"/reference/@neo-one/client/hash160abireturn","value":"Hash160ABIReturn"},{"value":";"},{"value":""}],"description":[{"value":""}]}},"current":"/reference/@neo-one/client","sidebar":[{"title":"Packages","subsections":[{"slug":"/reference/@neo-one/client","title":"@neo-one/client"},{"slug":"/reference/@neo-one/smart-contract","title":"@neo-one/smart-contract"}]}]},"path":"reference/@neo-one/client/hash160abi"}
